<?xml version="1.0" encoding="UTF-8" ?>
<GetFTPDataDetailsDBOutputCollection xmlns="http://xmlns.oracle.com/pcbpel/adapter/db/GetFTPDataDetailsDB">
   <GetFTPDataDetailsDBOutput>
      <TRX_NUMBER>TRX_NUMBER16</TRX_NUMBER>
      <BILL_TO_CUSTOMER_ID>17</BILL_TO_CUSTOMER_ID>
      <CUSTOMER_NUMBER>CUSTOMER_NUMBER18</CUSTOMER_NUMBER>
      <TRX_STATUS>TRX_STATUS19</TRX_STATUS>
      <TRX_DATE>2012-12-13T16:13:54.255</TRX_DATE>
      <TRX_CREATION_DATE>2012-12-13T16:13:54.255</TRX_CREATION_DATE>
      <TRX_TYPE>TRX_TYPE20</TRX_TYPE>
      <TRX_TYPE_NAME>TRX_TYPE_NAME21</TRX_TYPE_NAME>
      <TRX_TYPE_DESC>TRX_TYPE_DESC22</TRX_TYPE_DESC>
      <OPERATING_UNIT_NAME>OPERATING_UNIT_NAME23</OPERATING_UNIT_NAME>
      <CURRENCY_CODE>CURRENCY_CODE24</CURRENCY_CODE>
      <TRANSACTION_CURRENCY_CODE>TRANSACTION_CURRENCY_CODE25</TRANSACTION_CURRENCY_CODE>
      <LAST_UPDATE_DATE>2012-12-13T16:13:54.256</LAST_UPDATE_DATE>
      <CREATED_BY>26</CREATED_BY>
      <LAST_UPDATED_BY>27</LAST_UPDATED_BY>
      <LAST_UPDATED_LOGIN>28</LAST_UPDATED_LOGIN>
      <RECORD_STATUS>RECORD_STATUS29</RECORD_STATUS>
      <RECORD_ID>30</RECORD_ID>
      <ERROR_MESSAGE>ERROR_MESSAGE31</ERROR_MESSAGE>
      <PDF_FILE_NAME>PDF_FILE_NAME32</PDF_FILE_NAME>
      <TRX_LAST_UPDATED_DATE>2012-12-13T16:13:54.256</TRX_LAST_UPDATED_DATE>
      <T_CREATION_DATE>T_CREATION_DATE33</T_CREATION_DATE>
      <TRX_TYPE_MEANING>TRX_TYPE_MEANING34</TRX_TYPE_MEANING>
      <ORG_ID>35</ORG_ID>
   </GetFTPDataDetailsDBOutput>
   <GetFTPDataDetailsDBOutput>
      <TRX_NUMBER>TRX_NUMBER36</TRX_NUMBER>
      <BILL_TO_CUSTOMER_ID>37</BILL_TO_CUSTOMER_ID>
      <CUSTOMER_NUMBER>CUSTOMER_NUMBER38</CUSTOMER_NUMBER>
      <TRX_STATUS>TRX_STATUS39</TRX_STATUS>
      <TRX_DATE>2012-12-13T16:13:54.256</TRX_DATE>
      <TRX_CREATION_DATE>2012-12-13T16:13:54.256</TRX_CREATION_DATE>
      <TRX_TYPE>TRX_TYPE40</TRX_TYPE>
      <TRX_TYPE_NAME>TRX_TYPE_NAME41</TRX_TYPE_NAME>
      <TRX_TYPE_DESC>TRX_TYPE_DESC42</TRX_TYPE_DESC>
      <OPERATING_UNIT_NAME>OPERATING_UNIT_NAME43</OPERATING_UNIT_NAME>
      <CURRENCY_CODE>CURRENCY_CODE44</CURRENCY_CODE>
      <TRANSACTION_CURRENCY_CODE>TRANSACTION_CURRENCY_CODE45</TRANSACTION_CURRENCY_CODE>
      <LAST_UPDATE_DATE>2012-12-13T16:13:54.256</LAST_UPDATE_DATE>
      <CREATED_BY>46</CREATED_BY>
      <LAST_UPDATED_BY>47</LAST_UPDATED_BY>
      <LAST_UPDATED_LOGIN>48</LAST_UPDATED_LOGIN>
      <RECORD_STATUS>RECORD_STATUS49</RECORD_STATUS>
      <RECORD_ID>50</RECORD_ID>
      <ERROR_MESSAGE>ERROR_MESSAGE51</ERROR_MESSAGE>
      <PDF_FILE_NAME>PDF_FILE_NAME52</PDF_FILE_NAME>
      <TRX_LAST_UPDATED_DATE>2012-12-13T16:13:54.257</TRX_LAST_UPDATED_DATE>
      <T_CREATION_DATE>T_CREATION_DATE53</T_CREATION_DATE>
      <TRX_TYPE_MEANING>TRX_TYPE_MEANING54</TRX_TYPE_MEANING>
      <ORG_ID>55</ORG_ID>
   </GetFTPDataDetailsDBOutput>
   <GetFTPDataDetailsDBOutput>
      <TRX_NUMBER>TRX_NUMBER56</TRX_NUMBER>
      <BILL_TO_CUSTOMER_ID>57</BILL_TO_CUSTOMER_ID>
      <CUSTOMER_NUMBER>CUSTOMER_NUMBER58</CUSTOMER_NUMBER>
      <TRX_STATUS>TRX_STATUS59</TRX_STATUS>
      <TRX_DATE>2012-12-13T16:13:54.257</TRX_DATE>
      <TRX_CREATION_DATE>2012-12-13T16:13:54.257</TRX_CREATION_DATE>
      <TRX_TYPE>TRX_TYPE60</TRX_TYPE>
      <TRX_TYPE_NAME>TRX_TYPE_NAME61</TRX_TYPE_NAME>
      <TRX_TYPE_DESC>TRX_TYPE_DESC62</TRX_TYPE_DESC>
      <OPERATING_UNIT_NAME>OPERATING_UNIT_NAME63</OPERATING_UNIT_NAME>
      <CURRENCY_CODE>CURRENCY_CODE64</CURRENCY_CODE>
      <TRANSACTION_CURRENCY_CODE>TRANSACTION_CURRENCY_CODE65</TRANSACTION_CURRENCY_CODE>
      <LAST_UPDATE_DATE>2012-12-13T16:13:54.257</LAST_UPDATE_DATE>
      <CREATED_BY>66</CREATED_BY>
      <LAST_UPDATED_BY>67</LAST_UPDATED_BY>
      <LAST_UPDATED_LOGIN>68</LAST_UPDATED_LOGIN>
      <RECORD_STATUS>RECORD_STATUS69</RECORD_STATUS>
      <RECORD_ID>70</RECORD_ID>
      <ERROR_MESSAGE>ERROR_MESSAGE71</ERROR_MESSAGE>
      <PDF_FILE_NAME>PDF_FILE_NAME72</PDF_FILE_NAME>
      <TRX_LAST_UPDATED_DATE>2012-12-13T16:13:54.257</TRX_LAST_UPDATED_DATE>
      <T_CREATION_DATE>T_CREATION_DATE73</T_CREATION_DATE>
      <TRX_TYPE_MEANING>TRX_TYPE_MEANING74</TRX_TYPE_MEANING>
      <ORG_ID>75</ORG_ID>
   </GetFTPDataDetailsDBOutput>
</GetFTPDataDetailsDBOutputCollection>
